Metadata-Version: 2.1
Name: sap-ecs-aws-log-forwarder
Version: 1.0.7
Summary: A package to consume events from an AWS SQS queue, process log files, and forward them to a HTTP endpoint or file.
Home-page: https://www.sap.com/
License: SAP DEVELOPER LICENSE AGREEMENT
Keywords: SAP AWS Log Forwarder,SAP Log Forwarder
Author: SAP SE
Requires-Python: >=3.10,<4.0
Classifier: Development Status :: 5 - Production/Stable
Classifier: Intended Audience :: Developers
Classifier: License :: Other/Proprietary License
Classifier: Operating System :: MacOS :: MacOS X
Classifier: Operating System :: POSIX :: Linux
Classifier: Programming Language :: Python :: 3
Classifier: Programming Language :: Python :: 3.10
Classifier: Programming Language :: Python :: 3.11
Classifier: Programming Language :: Python :: 3.12
Classifier: Topic :: Software Development :: Libraries :: Python Modules
Requires-Dist: boto3 (>=1.17.49,<2.0.0)
Requires-Dist: cryptography (>=44.0.1,<45.0.0)
Requires-Dist: requests (>=2.32.4,<3.0.0)
Requires-Dist: urllib3 (>=2.5.0,<3.0.0)
